eo_client/__init__.py
eo_client/api_client.py
eo_client/configuration.py
eo_client/rest.py
eo_client/api/__init__.py
eo_client/api/atomic_projects_api.py
eo_client/api/complex_projects_api.py
eo_client/api/organization_teams_api.py
eo_client/api/organizational_roles_api.py
eo_client/api/organizations_api.py
eo_client/api/people_api.py
eo_client/api/project_teams_api.py
eo_client/api/projects_api.py
eo_client/api/team_members_api.py
eo_client/api/team_memberships_api.py
eo_client/api/team_purposes_api.py
eo_client/api/teams_api.py
eo_client/models/__init__.py
eo_client/models/atomic_project_.py
eo_client/models/complex_project_.py
eo_client/models/organization_.py
eo_client/models/organization_team_.py
eo_client/models/organizational_role_.py
eo_client/models/person_.py
eo_client/models/project_.py
eo_client/models/project_team_.py
eo_client/models/team_.py
eo_client/models/team_member_.py
eo_client/models/team_membership_.py
eo_client/models/team_purpose_.py
test/__init__.py
test/test_atomic_project_.py
test/test_atomic_projects_api.py
test/test_complex_project_.py
test/test_complex_projects_api.py
test/test_organization_.py
test/test_organization_team_.py
test/test_organization_teams_api.py
test/test_organizational_role_.py
test/test_organizational_roles_api.py
test/test_organizations_api.py
test/test_people_api.py
test/test_person_.py
test/test_project_.py
test/test_project_team_.py
test/test_project_teams_api.py
test/test_projects_api.py
test/test_team_.py
test/test_team_member_.py
test/test_team_members_api.py
test/test_team_membership_.py
test/test_team_memberships_api.py
test/test_team_purpose_.py
test/test_team_purposes_api.py
test/test_teams_api.py
eo_client-1.0.20.dist-info/METADATA
eo_client-1.0.20.dist-info/WHEEL
eo_client-1.0.20.dist-info/top_level.txt
eo_client-1.0.20.dist-info/RECORD
